{
  "$schema": "https://schema.tauri.app/acl/2",
  "identifier": "default",
  "description": "Wilson Term default capabilities",
  "windows": ["main"],
  "permissions": [
    "core:default",
    "core:window:default",
    "core:window:allow-minimize",
    "core:window:allow-maximize",
    "core:window:allow-unmaximize",
    "core:window:allow-close",
    "core:window:allow-is-maximized",
    "core:window:allow-start-dragging",
    "core:webview:allow-internal-toggle-devtools",
    "opener:allow-open-url",
    "opener:allow-open-path",
    "dialog:allow-open",
    "dialog:allow-save",
    "fs:allow-read-file",
    "fs:allow-write-file",
    "updater:default",
    "store:default"
  ]
}
